Metadata-Version: 2.4
Name: dicom-mcp-enhanced
Version: 0.1.1
Summary: Enhanced DICOM MCP Server for Medical Imaging Systems
Author-email: KainYin <yinkain694@gmail.com>
Requires-Python: >=3.12
License-File: LICENSE
Requires-Dist: httpx>=0.28.1
Requires-Dist: mcp[cli]>=1.3.0
Requires-Dist: pynetdicom>=2.1.1
Requires-Dist: pypdf2>=3.0.1
Requires-Dist: pyyaml>=6.0.2
Provides-Extra: dev
Requires-Dist: pytest>=7.4.0; extra == "dev"
Requires-Dist: requests>=2.31.0; extra == "dev"
Requires-Dist: pydicom>=2.4.0; extra == "dev"
Requires-Dist: pytest-cov>=6.0.0; extra == "dev"
Requires-Dist: reportlab; extra == "dev"
Requires-Dist: nibabel>=5.0.0; extra == "dev"
Requires-Dist: numpy>=1.24.0; extra == "dev"
Dynamic: license-file
